manim_speech/__init__.py
manim_speech/scene.py
manim_speech/services/__init__.py
manim_speech/services/assemblyai.py
manim_speech/services/base.py
manim_speech/services/deepl.py
manim_speech/services/elevenlabs.py
manim_speech/services/openai.py
manim_speech/services/whisper.py
manim_speech/speech.py
manim_speech/translation.py
manim_speech-0.2.1.dist-info/LICENSE
manim_speech-0.2.1.dist-info/METADATA
manim_speech-0.2.1.dist-info/WHEEL
manim_speech-0.2.1.dist-info/RECORD
