Metadata-Version: 2.1
Name: manim_speech
Version: 0.2.1
Summary: Manim plugin for adding speech to videos.
Home-page: https://github.com/MtCelesteMa/manim-speech
License: MIT
Keywords: manim,speech,voiceover,tts
Author: Celeste Ma
Author-email: mtcelestema@proton.me
Requires-Python: >=3.12,<3.13
Classifier: Development Status :: 4 - Beta
Classifier: Intended Audience :: Science/Research
Classifier: License :: OSI Approved :: MIT License
Classifier: Programming Language :: Python :: 3
Classifier: Programming Language :: Python :: 3.12
Classifier: Topic :: Multimedia :: Sound/Audio :: Speech
Provides-Extra: assemblyai
Provides-Extra: chinese
Provides-Extra: deepl
Provides-Extra: elevenlabs
Provides-Extra: openai
Requires-Dist: assemblyai (>=0.28.1,<0.29.0) ; extra == "assemblyai"
Requires-Dist: deepl (>=1.18.0,<2.0.0) ; extra == "deepl"
Requires-Dist: elevenlabs (>=1.3.1,<2.0.0) ; extra == "elevenlabs"
Requires-Dist: langconv (>=0.3.0,<0.4.0) ; extra == "chinese"
Requires-Dist: manim (>=0.18.1,<0.19.0)
Requires-Dist: mutagen (>=1.47.0,<2.0.0)
Requires-Dist: openai (>=1.35.9,<2.0.0) ; extra == "openai"
Requires-Dist: polib (>=1.2.0,<2.0.0)
Requires-Dist: pydantic (>=2.8.0,<3.0.0)
Project-URL: Repository, https://github.com/MtCelesteMa/manim-speech
